{
  "id": "animepahe-provider",
  "name": "Animepahe Streaming",
  "description": "Scrapes and streams media assets directly from animepahe.ch.",
  "manifestURI": "",
  "version": "1.0.0",
  "author": "tetolinux",
  "type": "onlinestream-provider",
  "language": "typescript",
  "lang": "en",
  "payload": "class Provider {\n    api = \"https://animepahe.ch\";\n    headers = {\n        \"User-Agent\": \"Mozilla/5.0 (Windows NT 10.0; Win64; x64) AppleWebKit/537.36 (KHTML, like Gecko) Chrome/120.0.0.0 Safari/537.36\",\n        \"Referer\": \"https://animepahe.ch/\"\n    };\n    getSettings() {\n        return {\n            episodeServers: [\"HD 1\", \"HD 2\", \"HD 3\"],\n            supportsDub: true\n        };\n    }\n    async search(opts) {\n        const req = await fetch(`${this.api}/?s=${encodeURIComponent(opts.query)}`, { headers: this.headers });\n        if (!req.ok) return [];\n        const html = await req.text();\n        const $ = LoadDoc(html);\n        const results = [];\n        $(\".listupd article.bs\").each((_, el) => {\n            const anchor = $(el).find(\"a\");\n            const title = anchor.attr(\"title\") || $(el).find(\"h2\").text();\n            const url = anchor.attr(\"href\") || \"\";\n            const typeText = $(el).find(\".sb\").text().toLowerCase();\n            let subOrDub = \"sub\";\n            if (typeText.includes(\"dub\")) subOrDub = \"dub\";\n            if (typeText.includes(\"both\")) subOrDub = \"both\";\n            const id = url.replace(this.api, \"\").replace(/\\/$/, \"\");\n            if (title && id) {\n                results.push({ id, title, url, subOrDub });\n            }\n        });\n        return results;\n    }\n    async findEpisodes(id) {\n        const targetUrl = id.startsWith(\"http\") ? id : `${this.api}${id}`;\n        const req = await fetch(targetUrl, { headers: this.headers });\n        if (!req.ok) throw new Error(\"Failed to load episode index mapping details.\");\n        const html = await req.text();\n        const $ = LoadDoc(html);\n        const episodes = [];\n        $(\".episodelist ul li\").each((_, el) => {\n            const anchor = $(el).find(\"a\");\n            const url = anchor.attr(\"href\") || \"\";\n            const title = anchor.find(\"h3\").text().trim();\n            const infoText = anchor.find(\".playinfo span\").text();\n            const epMatch = infoText.match(/Eps\\s*(\\d+)/i);\n            const epNumber = epMatch ? parseInt(epMatch[1], 10) : episodes.length + 1;\n            const epId = url.replace(this.api, \"\").replace(/\\/$/, \"\");\n            if (epId) {\n                episodes.push({ id: epId, number: epNumber, url, title: title || `Episode ${epNumber}` });\n            }\n        });\n        return episodes.reverse();\n    }\n    async findEpisodeServer(episode, _server) {\n        const targetUrl = episode.id.startsWith(\"http\") ? episode.id : `${this.api}${episode.id}`;\n        const req = await fetch(targetUrl, { headers: this.headers });\n        if (!req.ok) throw new Error(\"Could not access targeted multi-server gateway panel.\");\n        const html = await req.text();\n        const $ = LoadDoc(html);\n        let targetIndex = 0;\n        if (_server === \"HD 2\") targetIndex = 1;\n        if (_server === \"HD 3\") targetIndex = 2;\n        const embedTab = $(\`.gov-all-host .gov-the-embed[data-index='${targetIndex}']\`);\n        if (!embedTab.length) throw new Error(`Requested video host mirror configuration [${_server}] is unavailable.`);\n        const onClickAttr = embedTab.attr(\"onclick\") || \"\";\n        const base64Match = onClickAttr.match(/putMi\\(\\s*this\\s*,\\s*'(.*?)'\\s*\\)/);\n        if (!base64Match || !base64Match[1]) throw new Error(\"Unable to parse inner encrypted server source data strings.\");\n        const decodedIframeHtml = atob(base64Match[1]);\n        const iframe$ = LoadDoc(decodedIframeHtml);\n        const videoEmbedUrl = iframe$(\"iframe\").attr(\"src\") || \"\";\n        if (!videoEmbedUrl) throw new Error(\"Failed to extract external network stream video source context parameters.\");\n        const videoSources = [];\n        if (videoEmbedUrl.includes(\"blogger.com\")) {\n            videoSources.push({ url: videoEmbedUrl, type: \"unknown\", quality: \"Blogger HD Stream (Default)\", subtitles: [] });\n        } else if (videoEmbedUrl.includes(\"ok.ru\")) {\n            videoSources.push({ url: videoEmbedUrl.startsWith(\"//\") ? `https:${videoEmbedUrl}` : videoEmbedUrl, type: \"unknown\", quality: \"OK.ru Mirror Premium\", subtitles: [] });\n        } else {\n            videoSources.push({ url: videoEmbedUrl, type: videoEmbedUrl.includes(\".m3u8\") ? \"m3u8\" : \"unknown\", quality: \"Alternative Direct Feed\", subtitles: [] });\n        }\n        return {\n            server: _server === \"default\" ? \"HD 1\" : _server,\n            headers: { ...this.headers, \"Referer\": this.api },\n            videoSources\n        };\n    }\n}"
}
